squigglepy/__init__.py
squigglepy/bayes.py
squigglepy/correlation.py
squigglepy/distributions.py
squigglepy/numbers.py
squigglepy/rng.py
squigglepy/samplers.py
squigglepy/utils.py
squigglepy/version.py
squigglepy-0.29.dist-info/LICENSE
squigglepy-0.29.dist-info/METADATA
squigglepy-0.29.dist-info/WHEEL
squigglepy-0.29.dist-info/RECORD
