Metadata-Version: 2.3
Name: squigglepy
Version: 0.29
Summary: Squiggle programming language for intuitive probabilistic estimation features in Python
License: MIT
Author: Peter Wildeford
Author-email: peter@rethinkpriorities.org
Requires-Python: >=3.9,<3.12
Classifier: Development Status :: 3 - Alpha
Classifier: License :: OSI Approved :: MIT License
Classifier: Operating System :: OS Independent
Classifier: Programming Language :: Python :: 3
Classifier: Programming Language :: Python :: 3.9
Classifier: Programming Language :: Python :: 3.10
Classifier: Programming Language :: Python :: 3.11
Provides-Extra: all
Provides-Extra: ecosystem
Provides-Extra: plots
Requires-Dist: matplotlib (>=3.7.1,<4.0.0) ; extra == "plots"
Requires-Dist: msgspec (>=0.15.1,<0.16.0)
Requires-Dist: numpy (>=1.24.3,<2.0.0)
Requires-Dist: pandas (>=2.0.2,<3.0.0) ; extra == "ecosystem"
Requires-Dist: pathos (>=0.3.0,<0.4.0)
Requires-Dist: scipy (>=1.10.1,<2.0.0)
Requires-Dist: setuptools (>=69.0.0,<70.0.0)
Requires-Dist: tqdm (>=4.65.0,<5.0.0)
Project-URL: Repository, https://github.com/rethinkpriorities/squigglepy
